twingly_search/__init__.py
twingly_search/client.py
twingly_search/constants.py
twingly_search/errors.py
twingly_search/parser.py
twingly_search/post.py
twingly_search/query.py
twingly_search/result.py
twingly_search-2.1.4.dist-info/METADATA
twingly_search-2.1.4.dist-info/WHEEL
twingly_search-2.1.4.dist-info/top_level.txt
twingly_search-2.1.4.dist-info/RECORD
