Metadata-Version: 2.1
Name: twingly-search
Version: 2.1.4
Summary: Python library for Twingly Search API
Home-page: https://github.com/twingly/twingly-search-api-python
Author: Twingly AB
Author-email: support@twingly.com
License: MIT
Keywords: twingly
Platform: UNKNOWN
Classifier: Development Status :: 5 - Production/Stable
Classifier: Intended Audience :: Developers
Classifier: License :: OSI Approved :: Apache Software License
Classifier: Operating System :: OS Independent
Classifier: Topic :: Software Development :: Libraries :: Python Modules
Classifier: Topic :: Internet
Classifier: Programming Language :: Python
Classifier: Programming Language :: Python :: 2
Classifier: Programming Language :: Python :: 2.7
Classifier: Programming Language :: Python :: 3
Classifier: Programming Language :: Python :: 3.5
Requires-Dist: future
Requires-Dist: requests
Requires-Dist: pytz
Requires-Dist: deprecation
